readpub/__init__.py
readpub/__version__.py
readpub/_typing.py
readpub/core.py
readpub-0.0.0.dist-info/LICENSE
readpub-0.0.0.dist-info/METADATA
readpub-0.0.0.dist-info/WHEEL
readpub-0.0.0.dist-info/top_level.txt
readpub-0.0.0.dist-info/RECORD
