Metadata-Version: 2.1
Name: readpub
Version: 0.0.0
Summary: My reader.
Home-page: https://github.com/Chitaoji/myreader/
Author: Chitaoji
Author-email: 2360742040@qq.com
License: BSD
Classifier: License :: OSI Approved :: BSD License
Classifier: Programming Language :: Python
Classifier: Programming Language :: Python :: 3
Classifier: Programming Language :: Python :: 3.12
Requires-Python: >=3.12.4
License-File: LICENSE
